panchang/__init__.py
panchang-0.0.0.dist-info/LICENSE
panchang-0.0.0.dist-info/METADATA
panchang-0.0.0.dist-info/WHEEL
panchang-0.0.0.dist-info/RECORD
